[
    {
        "num": "199107",
        "stno": "467571",
        "WSMax": "11.5",
        "WDMax": "45.0",
        "WMaxTime": "",
        "WSGust": "19.4",
        "WDGust": "45.0",
        "WGustTime": "",
        "typhoon_name": "1991AMY",
        "typhoon_cht_name": "艾美"
    },
    {
        "num": "199107",
        "stno": "467571",
        "WSMax": "17.7",
        "WDMax": "67.5",
        "WMaxTime": "",
        "WSGust": "27.0",
        "WDGust": "67.5",
        "WGustTime": "",
        "typhoon_name": "1991AMY",
        "typhoon_cht_name": "艾美"
    },
    {
        "num": "199111",
        "stno": "467571",
        "WSMax": "9.0",
        "WDMax": "337.5",
        "WMaxTime": "",
        "WSGust": "12.5",
        "WDGust": "22.5",
        "WGustTime": "",
        "typhoon_name": "1991ELLIE",
        "typhoon_cht_name": "愛麗"
    },
    {
        "num": "199111",
        "stno": "467571",
        "WSMax": "10.3",
        "WDMax": "337.5",
        "WMaxTime": "",
        "WSGust": "15.0",
        "WDGust": "337.5",
        "WGustTime": "",
        "typhoon_name": "1991ELLIE",
        "typhoon_cht_name": "愛麗"
    },
    {
        "num": "199119",
        "stno": "467571",
        "WSMax": "6.2",
        "WDMax": "360.0",
        "WMaxTime": "",
        "WSGust": "13.9",
        "WDGust": "360.0",
        "WGustTime": "",
        "typhoon_name": "1991MIREILLE",
        "typhoon_cht_name": "密瑞兒"
    },
    {
        "num": "199119",
        "stno": "467571",
        "WSMax": "6.0",
        "WDMax": "67.5",
        "WMaxTime": "",
        "WSGust": "10.1",
        "WDGust": "67.5",
        "WGustTime": "",
        "typhoon_name": "1991MIREILLE",
        "typhoon_cht_name": "密瑞兒"
    },
    {
        "num": "199120",
        "stno": "467571",
        "WSMax": "16.7",
        "WDMax": "67.5",
        "WMaxTime": "",
        "WSGust": "23.1",
        "WDGust": "67.5",
        "WGustTime": "",
        "typhoon_name": "1991NAT",
        "typhoon_cht_name": "耐特"
    },
    {
        "num": "199120",
        "stno": "467571",
        "WSMax": "11.0",
        "WDMax": "67.5",
        "WMaxTime": "",
        "WSGust": "16.3",
        "WDGust": "67.5",
        "WGustTime": "",
        "typhoon_name": "1991NAT",
        "typhoon_cht_name": "耐特"
    },
    {
        "num": "199120",
        "stno": "467571",
        "WSMax": "5.0",
        "WDMax": "45.0",
        "WMaxTime": "",
        "WSGust": "8.5",
        "WDGust": "45.0",
        "WGustTime": "",
        "typhoon_name": "1991NAT",
        "typhoon_cht_name": "耐特"
    },
    {
        "num": "199120",
        "stno": "467571",
        "WSMax": "5.0",
        "WDMax": "360.0",
        "WMaxTime": "",
        "WSGust": "6.4",
        "WDGust": "360.0",
        "WGustTime": "",
        "typhoon_name": "1991NAT",
        "typhoon_cht_name": "耐特"
    },
    {
        "num": "199123",
        "stno": "467571",
        "WSMax": "12.2",
        "WDMax": "67.5",
        "WMaxTime": "",
        "WSGust": "22.1",
        "WDGust": "67.5",
        "WGustTime": "",
        "typhoon_name": "1991RUTH",
        "typhoon_cht_name": "露絲"
    },
    {
        "num": "199123",
        "stno": "467571",
        "WSMax": "13.5",
        "WDMax": "45.0",
        "WMaxTime": "",
        "WSGust": "26.6",
        "WDGust": "67.5",
        "WGustTime": "",
        "typhoon_name": "1991RUTH",
        "typhoon_cht_name": "露絲"
    },
    {
        "num": "199123",
        "stno": "467571",
        "WSMax": "12.1",
        "WDMax": "67.5",
        "WMaxTime": "",
        "WSGust": "20.8",
        "WDGust": "67.5",
        "WGustTime": "",
        "typhoon_name": "1991RUTH",
        "typhoon_cht_name": "露絲"
    },
    {
        "num": "199123",
        "stno": "467571",
        "WSMax": "13.5",
        "WDMax": "45.0",
        "WMaxTime": "",
        "WSGust": "22.5",
        "WDGust": "45.0",
        "WGustTime": "",
        "typhoon_name": "1991RUTH",
        "typhoon_cht_name": "露絲"
    },
    {
        "num": "199124",
        "stno": "467571",
        "WSMax": "14.0",
        "WDMax": "45.0",
        "WMaxTime": "",
        "WSGust": "24.5",
        "WDGust": "45.0",
        "WGustTime": "",
        "typhoon_name": "1991SETH",
        "typhoon_cht_name": "席斯"
    },
    {
        "num": "199124",
        "stno": "467571",
        "WSMax": "11.3",
        "WDMax": "45.0",
        "WMaxTime": "",
        "WSGust": "19.3",
        "WDGust": "45.0",
        "WGustTime": "",
        "typhoon_name": "1991SETH",
        "typhoon_cht_name": "席斯"
    },
    {
        "num": "199202",
        "stno": "467571",
        "WSMax": "12.3",
        "WDMax": "45.0",
        "WMaxTime": "",
        "WSGust": "21.6",
        "WDGust": "22.5",
        "WGustTime": "",
        "typhoon_name": "1992BOBBIE",
        "typhoon_cht_name": "芭比"
    },
    {
        "num": "199202",
        "stno": "467571",
        "WSMax": "7.7",
        "WDMax": "22.5",
        "WMaxTime": "",
        "WSGust": "12.2",
        "WDGust": "45.0",
        "WGustTime": "",
        "typhoon_name": "1992BOBBIE",
        "typhoon_cht_name": "芭比"
    },
    {
        "num": "199213",
        "stno": "467571",
        "WSMax": "9.8",
        "WDMax": "67.5",
        "WMaxTime": "",
        "WSGust": "18.5",
        "WDGust": "90.0",
        "WGustTime": "",
        "typhoon_name": "1992MARK",
        "typhoon_cht_name": "馬克"
    },
    {
        "num": "199213",
        "stno": "467571",
        "WSMax": "5.1",
        "WDMax": "90.0",
        "WMaxTime": "",
        "WSGust": "8.9",
        "WDGust": "90.0",
        "WGustTime": "",
        "typhoon_name": "1992MARK",
        "typhoon_cht_name": "馬克"
    },
    {
        "num": "199215",
        "stno": "467571",
        "WSMax": "13.7",
        "WDMax": "45.0",
        "WMaxTime": "",
        "WSGust": "25.4",
        "WDGust": "45.0",
        "WGustTime": "",
        "typhoon_name": "1992OMAR",
        "typhoon_cht_name": "歐馬"
    },
    {
        "num": "199215",
        "stno": "467571",
        "WSMax": "11.5",
        "WDMax": "45.0",
        "WMaxTime": "",
        "WSGust": "19.0",
        "WDGust": "45.0",
        "WGustTime": "",
        "typhoon_name": "1992OMAR",
        "typhoon_cht_name": "歐馬"
    },
    {
        "num": "199216",
        "stno": "467571",
        "WSMax": "10.0",
        "WDMax": "45.0",
        "WMaxTime": "",
        "WSGust": "17.4",
        "WDGust": "67.5",
        "WGustTime": "",
        "typhoon_name": "1992POLLY",
        "typhoon_cht_name": "寶莉"
    },
    {
        "num": "199216",
        "stno": "467571",
        "WSMax": "12.2",
        "WDMax": "45.0",
        "WMaxTime": "",
        "WSGust": "20.0",
        "WDGust": "45.0",
        "WGustTime": "",
        "typhoon_name": "1992POLLY",
        "typhoon_cht_name": "寶莉"
    },
    {
        "num": "199216",
        "stno": "467571",
        "WSMax": "11.9",
        "WDMax": "22.5",
        "WMaxTime": "",
        "WSGust": "22.3",
        "WDGust": "22.5",
        "WGustTime": "",
        "typhoon_name": "1992POLLY",
        "typhoon_cht_name": "寶莉"
    },
    {
        "num": "199216",
        "stno": "467571",
        "WSMax": "6.1",
        "WDMax": "202.5",
        "WMaxTime": "",
        "WSGust": "11.4",
        "WDGust": "202.5",
        "WGustTime": "",
        "typhoon_name": "1992POLLY",
        "typhoon_cht_name": "寶莉"
    },
    {
        "num": "199219",
        "stno": "467571",
        "WSMax": "11.9",
        "WDMax": "67.5",
        "WMaxTime": "",
        "WSGust": "21.4",
        "WDGust": "45.0",
        "WGustTime": "",
        "typhoon_name": "1992TED",
        "typhoon_cht_name": "泰德"
    },
    {
        "num": "199219",
        "stno": "467571",
        "WSMax": "12.0",
        "WDMax": "45.0",
        "WMaxTime": "",
        "WSGust": "21.5",
        "WDGust": "45.0",
        "WGustTime": "",
        "typhoon_name": "1992TED",
        "typhoon_cht_name": "泰德"
    },
    {
        "num": "199219",
        "stno": "467571",
        "WSMax": "9.2",
        "WDMax": "270.0",
        "WMaxTime": "",
        "WSGust": "20.8",
        "WDGust": "202.5",
        "WGustTime": "",
        "typhoon_name": "1992TED",
        "typhoon_cht_name": "泰德"
    },
    {
        "num": "199311",
        "stno": "467571",
        "WSMax": "5.2",
        "WDMax": "247.5",
        "WMaxTime": "",
        "WSGust": "8.3",
        "WDGust": "270.0",
        "WGustTime": "",
        "typhoon_name": "1993TASHA",
        "typhoon_cht_name": "塔莎"
    },
    {
        "num": "199314",
        "stno": "467571",
        "WSMax": "8.7",
        "WDMax": "45.0",
        "WMaxTime": "",
        "WSGust": "14.9",
        "WDGust": "22.5",
        "WGustTime": "",
        "typhoon_name": "1993YANCY",
        "typhoon_cht_name": "楊希"
    },
    {
        "num": "199314",
        "stno": "467571",
        "WSMax": "5.9",
        "WDMax": "22.5",
        "WMaxTime": "",
        "WSGust": "11.2",
        "WDGust": "360.0",
        "WGustTime": "",
        "typhoon_name": "1993YANCY",
        "typhoon_cht_name": "楊希"
    },
    {
        "num": "199413",
        "stno": "467571",
        "WSMax": "11.3",
        "WDMax": "360.0",
        "WMaxTime": "",
        "WSGust": "22.5",
        "WDGust": "247.5",
        "WGustTime": "",
        "typhoon_name": "1994DOUG",
        "typhoon_cht_name": "道格"
    },
    {
        "num": "199413",
        "stno": "467571",
        "WSMax": "14.0",
        "WDMax": "315.0",
        "WMaxTime": "",
        "WSGust": "28.8",
        "WDGust": "270.0",
        "WGustTime": "",
        "typhoon_name": "1994DOUG",
        "typhoon_cht_name": "道格"
    },
    {
        "num": "199415",
        "stno": "467571",
        "WSMax": "12.2",
        "WDMax": "22.5",
        "WMaxTime": "",
        "WSGust": "23.9",
        "WDGust": "45.0",
        "WGustTime": "",
        "typhoon_name": "1994FRED",
        "typhoon_cht_name": "弗雷特"
    },
    {
        "num": "199415",
        "stno": "467571",
        "WSMax": "10.8",
        "WDMax": "360.0",
        "WMaxTime": "",
        "WSGust": "17.8",
        "WDGust": "247.5",
        "WGustTime": "",
        "typhoon_name": "1994FRED",
        "typhoon_cht_name": "弗雷特"
    },
    {
        "num": "199416",
        "stno": "467571",
        "WSMax": "11.9",
        "WDMax": "360.0",
        "WMaxTime": "",
        "WSGust": "21.9",
        "WDGust": "360.0",
        "WGustTime": "",
        "typhoon_name": "1994GLADYS",
        "typhoon_cht_name": "葛拉絲"
    },
    {
        "num": "199427",
        "stno": "467571",
        "WSMax": "13.7",
        "WDMax": "67.5",
        "WMaxTime": "",
        "WSGust": "24.1",
        "WDGust": "67.5",
        "WGustTime": "",
        "typhoon_name": "1994SETH",
        "typhoon_cht_name": "席斯"
    },
    {
        "num": "199427",
        "stno": "467571",
        "WSMax": "9.3",
        "WDMax": "360.0",
        "WMaxTime": "",
        "WSGust": "22.8",
        "WDGust": "90.0",
        "WGustTime": "",
        "typhoon_name": "1994SETH",
        "typhoon_cht_name": "席斯"
    },
    {
        "num": "199427",
        "stno": "467571",
        "WSMax": "9.1",
        "WDMax": "337.5",
        "WMaxTime": "",
        "WSGust": "21.5",
        "WDGust": "360.0",
        "WGustTime": "",
        "typhoon_name": "1994SETH",
        "typhoon_cht_name": "席斯"
    },
    {
        "num": "199405",
        "stno": "467571",
        "WSMax": "18.2",
        "WDMax": "67.5",
        "WMaxTime": "",
        "WSGust": "33.0",
        "WDGust": "67.5",
        "WGustTime": "",
        "typhoon_name": "1994TIM",
        "typhoon_cht_name": "提姆"
    },
    {
        "num": "199502",
        "stno": "467571",
        "WSMax": "7.7",
        "WDMax": "22.5",
        "WMaxTime": "",
        "WSGust": "12.6",
        "WDGust": "45.0",
        "WGustTime": "",
        "typhoon_name": "1995DEANNA",
        "typhoon_cht_name": "荻安娜"
    },
    {
        "num": "199502",
        "stno": "467571",
        "WSMax": "5.8",
        "WDMax": "360.0",
        "WMaxTime": "",
        "WSGust": "10.6",
        "WDGust": "360.0",
        "WGustTime": "",
        "typhoon_name": "1995DEANNA",
        "typhoon_cht_name": "荻安娜"
    },
    {
        "num": "199502",
        "stno": "467571",
        "WSMax": "5.9",
        "WDMax": "22.5",
        "WMaxTime": "",
        "WSGust": "10.0",
        "WDGust": "22.5",
        "WGustTime": "",
        "typhoon_name": "1995DEANNA",
        "typhoon_cht_name": "荻安娜"
    },
    {
        "num": "199508",
        "stno": "467571",
        "WSMax": "5.2",
        "WDMax": "225.0",
        "WMaxTime": "",
        "WSGust": "11.5",
        "WDGust": "202.5",
        "WGustTime": "",
        "typhoon_name": "1995JANIS",
        "typhoon_cht_name": "珍妮絲"
    },
    {
        "num": "199509",
        "stno": "467571",
        "WSMax": "11.1",
        "WDMax": "45.0",
        "WMaxTime": "",
        "WSGust": "20.4",
        "WDGust": "67.5",
        "WGustTime": "",
        "typhoon_name": "1995KENT",
        "typhoon_cht_name": "肯特"
    },
    {
        "num": "199515",
        "stno": "467571",
        "WSMax": "8.8",
        "WDMax": "45.0",
        "WMaxTime": "",
        "WSGust": "16.3",
        "WDGust": "22.5",
        "WGustTime": "",
        "typhoon_name": "1995RYAN",
        "typhoon_cht_name": "賴恩"
    },
    {
        "num": "199515",
        "stno": "467571",
        "WSMax": "12.3",
        "WDMax": "22.5",
        "WMaxTime": "",
        "WSGust": "21.8",
        "WDGust": "22.5",
        "WGustTime": "",
        "typhoon_name": "1995RYAN",
        "typhoon_cht_name": "賴恩"
    },
    {
        "num": "199603",
        "stno": "467571",
        "WSMax": "6.3",
        "WDMax": "67.5",
        "WMaxTime": "",
        "WSGust": "10.8",
        "WDGust": "67.5",
        "WGustTime": "",
        "typhoon_name": "1996CAM",
        "typhoon_cht_name": "凱姆"
    },
    {
        "num": "199603",
        "stno": "467571",
        "WSMax": "7.6",
        "WDMax": "22.5",
        "WMaxTime": "",
        "WSGust": "12.6",
        "WDGust": "45.0",
        "WGustTime": "",
        "typhoon_name": "1996CAM",
        "typhoon_cht_name": "凱姆"
    },
    {
        "num": "199607",
        "stno": "467571",
        "WSMax": "10.6",
        "WDMax": "67.5",
        "WMaxTime": "",
        "WSGust": "17.5",
        "WDGust": "67.5",
        "WGustTime": "",
        "typhoon_name": "1996GLORIA",
        "typhoon_cht_name": "葛樂禮"
    },
    {
        "num": "199607",
        "stno": "467571",
        "WSMax": "11.4",
        "WDMax": "67.5",
        "WMaxTime": "",
        "WSGust": "20.8",
        "WDGust": "90.0",
        "WGustTime": "",
        "typhoon_name": "1996GLORIA",
        "typhoon_cht_name": "葛樂禮"
    },
    {
        "num": "199608",
        "stno": "467571",
        "WSMax": "8.5",
        "WDMax": "22.5",
        "WMaxTime": "",
        "WSGust": "16.5",
        "WDGust": "22.5",
        "WGustTime": "",
        "typhoon_name": "1996HERB",
        "typhoon_cht_name": "賀伯"
    },
    {
        "num": "199608",
        "stno": "467571",
        "WSMax": "16.2",
        "WDMax": "360.0",
        "WMaxTime": "",
        "WSGust": "29.8",
        "WDGust": "360.0",
        "WGustTime": "",
        "typhoon_name": "1996HERB",
        "typhoon_cht_name": "賀伯"
    },
    {
        "num": "199608",
        "stno": "467571",
        "WSMax": "15.6",
        "WDMax": "360.0",
        "WMaxTime": "",
        "WSGust": "27.8",
        "WDGust": "360.0",
        "WGustTime": "",
        "typhoon_name": "1996HERB",
        "typhoon_cht_name": "賀伯"
    },
    {
        "num": "199618",
        "stno": "467571",
        "WSMax": "7.0",
        "WDMax": "90.0",
        "WMaxTime": "",
        "WSGust": "14.6",
        "WDGust": "90.0",
        "WGustTime": "",
        "typhoon_name": "1996SALLY",
        "typhoon_cht_name": "莎莉"
    },
    {
        "num": "199623",
        "stno": "467571",
        "WSMax": "9.3",
        "WDMax": "360.0",
        "WMaxTime": "",
        "WSGust": "17.3",
        "WDGust": "360.0",
        "WGustTime": "",
        "typhoon_name": "1996ZANE",
        "typhoon_cht_name": "薩恩"
    },
    {
        "num": "199717",
        "stno": "467571",
        "WSMax": "11.5",
        "WDMax": "45.0",
        "WMaxTime": "",
        "WSGust": "24.5",
        "WDGust": "22.5",
        "WGustTime": "",
        "typhoon_name": "1997AMBER",
        "typhoon_cht_name": "安珀"
    },
    {
        "num": "199717",
        "stno": "467571",
        "WSMax": "14.2",
        "WDMax": "45.0",
        "WMaxTime": "",
        "WSGust": "28.4",
        "WDGust": "67.5",
        "WGustTime": "",
        "typhoon_name": "1997AMBER",
        "typhoon_cht_name": "安珀"
    },
    {
        "num": "199726",
        "stno": "467571",
        "WSMax": "5.2",
        "WDMax": "22.5",
        "WMaxTime": "",
        "WSGust": "8.4",
        "WDGust": "45.0",
        "WGustTime": "",
        "typhoon_name": "1997IVAN",
        "typhoon_cht_name": "艾文"
    },
    {
        "num": "199726",
        "stno": "467571",
        "WSMax": "6.5",
        "WDMax": "22.5",
        "WMaxTime": "",
        "WSGust": "11.3",
        "WDGust": "22.5",
        "WGustTime": "",
        "typhoon_name": "1997IVAN",
        "typhoon_cht_name": "艾文"
    },
    {
        "num": "199714",
        "stno": "467571",
        "WSMax": "7.1",
        "WDMax": "360.0",
        "WMaxTime": "",
        "WSGust": "17.2",
        "WDGust": "360.0",
        "WGustTime": "",
        "typhoon_name": "1997WINNIE",
        "typhoon_cht_name": "溫妮"
    },
    {
        "num": "199714",
        "stno": "467571",
        "WSMax": "9.9",
        "WDMax": "202.5",
        "WMaxTime": "",
        "WSGust": "18.9",
        "WDGust": "225.0",
        "WGustTime": "",
        "typhoon_name": "1997WINNIE",
        "typhoon_cht_name": "溫妮"
    },
    {
        "num": "199714",
        "stno": "467571",
        "WSMax": "6.8",
        "WDMax": "202.5",
        "WMaxTime": "",
        "WSGust": "14.8",
        "WDGust": "202.5",
        "WGustTime": "",
        "typhoon_name": "1997WINNIE",
        "typhoon_cht_name": "溫妮"
    },
    {
        "num": "199812",
        "stno": "467571",
        "WSMax": "9.7",
        "WDMax": "45.0",
        "WMaxTime": "",
        "WSGust": "18.4",
        "WDGust": "360.0",
        "WGustTime": "",
        "typhoon_name": "1998BABS",
        "typhoon_cht_name": "芭比絲"
    },
    {
        "num": "199812",
        "stno": "467571",
        "WSMax": "8.4",
        "WDMax": "45.0",
        "WMaxTime": "",
        "WSGust": "15.3",
        "WDGust": "22.5",
        "WGustTime": "",
        "typhoon_name": "1998BABS",
        "typhoon_cht_name": "芭比絲"
    },
    {
        "num": "199802",
        "stno": "467571",
        "WSMax": "5.8",
        "WDMax": "45.0",
        "WMaxTime": "",
        "WSGust": "11.7",
        "WDGust": "67.5",
        "WGustTime": "",
        "typhoon_name": "1998OTTO",
        "typhoon_cht_name": "奧托"
    },
    {
        "num": "199802",
        "stno": "467571",
        "WSMax": "7.2",
        "WDMax": "247.5",
        "WMaxTime": "",
        "WSGust": "15.3",
        "WDGust": "247.5",
        "WGustTime": "",
        "typhoon_name": "1998OTTO",
        "typhoon_cht_name": "奧托"
    },
    {
        "num": "199809",
        "stno": "467571",
        "WSMax": "7.3",
        "WDMax": "360.0",
        "WMaxTime": "",
        "WSGust": "13.5",
        "WDGust": "22.5",
        "WGustTime": "",
        "typhoon_name": "1998YANNI",
        "typhoon_cht_name": "楊妮"
    },
    {
        "num": "199810",
        "stno": "467571",
        "WSMax": "7.2",
        "WDMax": "67.5",
        "WMaxTime": "",
        "WSGust": "14.6",
        "WDGust": "90.0",
        "WGustTime": "",
        "typhoon_name": "1998ZEB",
        "typhoon_cht_name": "瑞珀"
    },
    {
        "num": "199810",
        "stno": "467571",
        "WSMax": "15.3",
        "WDMax": "22.5",
        "WMaxTime": "",
        "WSGust": "26.8",
        "WDGust": "45.0",
        "WGustTime": "",
        "typhoon_name": "1998ZEB",
        "typhoon_cht_name": "瑞珀"
    },
    {
        "num": "199810",
        "stno": "467571",
        "WSMax": "15.1",
        "WDMax": "360.0",
        "WMaxTime": "",
        "WSGust": "33.7",
        "WDGust": "360.0",
        "WGustTime": "",
        "typhoon_name": "1998ZEB",
        "typhoon_cht_name": "瑞珀"
    },
    {
        "num": "199810",
        "stno": "467571",
        "WSMax": "6.3",
        "WDMax": "22.5",
        "WMaxTime": "",
        "WSGust": "10.5",
        "WDGust": "22.5",
        "WGustTime": "",
        "typhoon_name": "1998ZEB",
        "typhoon_cht_name": "瑞珀"
    },
    {
        "num": "199920",
        "stno": "467571",
        "WSMax": "12.2",
        "WDMax": "45.0",
        "WMaxTime": "",
        "WSGust": "23.1",
        "WDGust": "45.0",
        "WGustTime": "",
        "typhoon_name": "1999DAN",
        "typhoon_cht_name": "丹恩"
    },
    {
        "num": "199906",
        "stno": "467571",
        "WSMax": "13.1",
        "WDMax": "45.0",
        "WMaxTime": "",
        "WSGust": "26.2",
        "WDGust": "22.5",
        "WGustTime": "",
        "typhoon_name": "1999MAGGIE",
        "typhoon_cht_name": "瑪姬"
    },
    {
        "num": "199906",
        "stno": "467571",
        "WSMax": "10.6",
        "WDMax": "67.5",
        "WMaxTime": "",
        "WSGust": "20.9",
        "WDGust": "45.0",
        "WGustTime": "",
        "typhoon_name": "1999MAGGIE",
        "typhoon_cht_name": "瑪姬"
    },
    {
        "num": "200010",
        "stno": "467571",
        "WSMax": "18.8",
        "WDMax": "30.0",
        "WMaxTime": "2000-08-22 22:59:00",
        "WSGust": "33.7",
        "WDGust": "70.0",
        "WGustTime": "2000-08-22 20:42:00",
        "typhoon_name": "2000BILIS",
        "typhoon_cht_name": "碧利斯"
    },
    {
        "num": "200010",
        "stno": "467571",
        "WSMax": "16.4",
        "WDMax": "40.0",
        "WMaxTime": "2000-08-23 00:22:00",
        "WSGust": "29.8",
        "WDGust": "70.0",
        "WGustTime": "2000-08-23 00:24:00",
        "typhoon_name": "2000BILIS",
        "typhoon_cht_name": "碧利斯"
    },
    {
        "num": "200015",
        "stno": "467571",
        "WSMax": "8.0",
        "WDMax": "30.0",
        "WMaxTime": "2000-09-09 23:16:00",
        "WSGust": "15.0",
        "WDGust": "40.0",
        "WGustTime": "2000-09-09 23:11:00",
        "typhoon_name": "2000BOPHA",
        "typhoon_cht_name": "寶發"
    },
    {
        "num": "200015",
        "stno": "467571",
        "WSMax": "9.8",
        "WDMax": "40.0",
        "WMaxTime": "2000-09-10 12:27:00",
        "WSGust": "17.1",
        "WDGust": "50.0",
        "WGustTime": "2000-09-10 12:25:00",
        "typhoon_name": "2000BOPHA",
        "typhoon_cht_name": "寶發"
    },
    {
        "num": "200004",
        "stno": "467571",
        "WSMax": "9.1",
        "WDMax": "40.0",
        "WMaxTime": "2000-07-07 14:40:00",
        "WSGust": "16.3",
        "WDGust": "60.0",
        "WGustTime": "2000-07-07 15:47:00",
        "typhoon_name": "2000KAI-TAK",
        "typhoon_cht_name": "啟德"
    },
    {
        "num": "200004",
        "stno": "467571",
        "WSMax": "8.8",
        "WDMax": "40.0",
        "WMaxTime": "2000-07-08 22:47:00",
        "WSGust": "15.2",
        "WDGust": "70.0",
        "WGustTime": "2000-07-08 19:54:00",
        "typhoon_name": "2000KAI-TAK",
        "typhoon_cht_name": "啟德"
    },
    {
        "num": "200004",
        "stno": "467571",
        "WSMax": "9.2",
        "WDMax": "40.0",
        "WMaxTime": "2000-07-09 01:09:00",
        "WSGust": "17.1",
        "WDGust": "110.0",
        "WGustTime": "2000-07-09 00:34:00",
        "typhoon_name": "2000KAI-TAK",
        "typhoon_cht_name": "啟德"
    },
    {
        "num": "200012",
        "stno": "467571",
        "WSMax": "7.3",
        "WDMax": "30.0",
        "WMaxTime": "2000-08-28 16:07:00",
        "WSGust": "14.5",
        "WDGust": "40.0",
        "WGustTime": "2000-08-28 16:01:00",
        "typhoon_name": "2000PRAPIROON",
        "typhoon_cht_name": "巴比侖"
    },
    {
        "num": "200012",
        "stno": "467571",
        "WSMax": "8.1",
        "WDMax": "360.0",
        "WMaxTime": "2000-08-29 20:56:00",
        "WSGust": "14.4",
        "WDGust": "40.0",
        "WGustTime": "2000-08-29 15:26:00",
        "typhoon_name": "2000PRAPIROON",
        "typhoon_cht_name": "巴比侖"
    },
    {
        "num": "200020",
        "stno": "467571",
        "WSMax": "16.3",
        "WDMax": "20.0",
        "WMaxTime": "2000-10-31 23:39:00",
        "WSGust": "29.6",
        "WDGust": "30.0",
        "WGustTime": "2000-10-31 23:10:00",
        "typhoon_name": "2000XANGSANE",
        "typhoon_cht_name": "象神"
    },
    {
        "num": "200020",
        "stno": "467571",
        "WSMax": "16.9",
        "WDMax": "20.0",
        "WMaxTime": "2000-11-01 00:05:00",
        "WSGust": "30.1",
        "WDGust": "50.0",
        "WGustTime": "2000-11-01 01:35:00",
        "typhoon_name": "2000XANGSANE",
        "typhoon_cht_name": "象神"
    },
    {
        "num": "200019",
        "stno": "467571",
        "WSMax": "8.6",
        "WDMax": "30.0",
        "WMaxTime": "2000-10-24 15:45:00",
        "WSGust": "14.2",
        "WDGust": "50.0",
        "WGustTime": "2000-10-24 16:48:00",
        "typhoon_name": "2000YAGI",
        "typhoon_cht_name": "雅吉"
    },
    {
        "num": "200019",
        "stno": "467571",
        "WSMax": "8.8",
        "WDMax": "30.0",
        "WMaxTime": "2000-10-25 10:54:00",
        "WSGust": "13.3",
        "WDGust": "60.0",
        "WGustTime": "2000-10-25 12:07:00",
        "typhoon_name": "2000YAGI",
        "typhoon_cht_name": "雅吉"
    },
    {
        "num": "200019",
        "stno": "467571",
        "WSMax": "10.6",
        "WDMax": "30.0",
        "WMaxTime": "2000-10-26 12:08:00",
        "WSGust": "18.2",
        "WDGust": "80.0",
        "WGustTime": "2000-10-26 13:08:00",
        "typhoon_name": "2000YAGI",
        "typhoon_cht_name": "雅吉"
    },
    {
        "num": "200101",
        "stno": "467571",
        "WSMax": "12.4",
        "WDMax": "50.0",
        "WMaxTime": "2001-05-12 14:15:00",
        "WSGust": "24.8",
        "WDGust": "70.0",
        "WGustTime": "2001-05-12 10:40:00",
        "typhoon_name": "2001CIMARON",
        "typhoon_cht_name": "西馬隆"
    },
    {
        "num": "200101",
        "stno": "467571",
        "WSMax": "9.4",
        "WDMax": "60.0",
        "WMaxTime": "2001-05-13 07:51:00",
        "WSGust": "17.4",
        "WDGust": "80.0",
        "WGustTime": "2001-05-13 09:47:00",
        "typhoon_name": "2001CIMARON",
        "typhoon_cht_name": "西馬隆"
    },
    {
        "num": "200121",
        "stno": "467571",
        "WSMax": "9.3",
        "WDMax": "10.0",
        "WMaxTime": "2001-10-16 11:04:00",
        "WSGust": "16.0",
        "WDGust": "30.0",
        "WGustTime": "2001-10-16 07:14:00",
        "typhoon_name": "2001HAIYAN",
        "typhoon_cht_name": "海燕"
    },
    {
        "num": "200119",
        "stno": "467571",
        "WSMax": "10.4",
        "WDMax": "30.0",
        "WMaxTime": "2001-09-24 11:39:00",
        "WSGust": "17.0",
        "WDGust": "90.0",
        "WGustTime": "2001-09-24 11:53:00",
        "typhoon_name": "2001LEKIMA",
        "typhoon_cht_name": "利奇馬"
    },
    {
        "num": "200119",
        "stno": "467571",
        "WSMax": "12.1",
        "WDMax": "30.0",
        "WMaxTime": "2001-09-25 22:16:00",
        "WSGust": "21.8",
        "WDGust": "50.0",
        "WGustTime": "2001-09-25 22:13:00",
        "typhoon_name": "2001LEKIMA",
        "typhoon_cht_name": "利奇馬"
    },
    {
        "num": "200119",
        "stno": "467571",
        "WSMax": "12.6",
        "WDMax": "40.0",
        "WMaxTime": "2001-09-26 14:26:00",
        "WSGust": "22.0",
        "WDGust": "60.0",
        "WGustTime": "2001-09-26 14:22:00",
        "typhoon_name": "2001LEKIMA",
        "typhoon_cht_name": "利奇馬"
    },
    {
        "num": "200119",
        "stno": "467571",
        "WSMax": "9.8",
        "WDMax": "50.0",
        "WMaxTime": "2001-09-27 00:09:00",
        "WSGust": "16.3",
        "WDGust": "90.0",
        "WGustTime": "2001-09-27 00:10:00",
        "typhoon_name": "2001LEKIMA",
        "typhoon_cht_name": "利奇馬"
    },
    {
        "num": "200119",
        "stno": "467571",
        "WSMax": "6.5",
        "WDMax": "30.0",
        "WMaxTime": "2001-09-28 10:28:00",
        "WSGust": "11.6",
        "WDGust": "70.0",
        "WGustTime": "2001-09-28 10:26:00",
        "typhoon_name": "2001LEKIMA",
        "typhoon_cht_name": "利奇馬"
    },
    {
        "num": "200116",
        "stno": "467571",
        "WSMax": "6.8",
        "WDMax": "30.0",
        "WMaxTime": "2001-09-09 14:49:00",
        "WSGust": "11.7",
        "WDGust": "50.0",
        "WGustTime": "2001-09-09 15:17:00",
        "typhoon_name": "2001NARI",
        "typhoon_cht_name": "納莉"
    },
    {
        "num": "200116",
        "stno": "467571",
        "WSMax": "5.8",
        "WDMax": "30.0",
        "WMaxTime": "2001-09-10 14:35:00",
        "WSGust": "9.6",
        "WDGust": "60.0",
        "WGustTime": "2001-09-10 13:59:00",
        "typhoon_name": "2001NARI",
        "typhoon_cht_name": "納莉"
    },
    {
        "num": "200116",
        "stno": "467571",
        "WSMax": "10.1",
        "WDMax": "10.0",
        "WMaxTime": "2001-09-16 23:49:00",
        "WSGust": "18.9",
        "WDGust": "60.0",
        "WGustTime": "2001-09-16 23:50:00",
        "typhoon_name": "2001NARI",
        "typhoon_cht_name": "納莉"
    },
    {
        "num": "200116",
        "stno": "467571",
        "WSMax": "12.4",
        "WDMax": "10.0",
        "WMaxTime": "2001-09-17 00:44:00",
        "WSGust": "21.5",
        "WDGust": "50.0",
        "WGustTime": "2001-09-17 23:45:00",
        "typhoon_name": "2001NARI",
        "typhoon_cht_name": "納莉"
    },
    {
        "num": "200116",
        "stno": "467571",
        "WSMax": "13.2",
        "WDMax": "10.0",
        "WMaxTime": "2001-09-18 06:38:00",
        "WSGust": "20.9",
        "WDGust": "30.0",
        "WGustTime": "2001-09-18 06:33:00",
        "typhoon_name": "2001NARI",
        "typhoon_cht_name": "納莉"
    },
    {
        "num": "200116",
        "stno": "467571",
        "WSMax": "7.2",
        "WDMax": "30.0",
        "WMaxTime": "2001-09-19 01:01:00",
        "WSGust": "11.4",
        "WDGust": "60.0",
        "WGustTime": "2001-09-19 01:08:00",
        "typhoon_name": "2001NARI",
        "typhoon_cht_name": "納莉"
    },
    {
        "num": "200108",
        "stno": "467571",
        "WSMax": "9.1",
        "WDMax": "30.0",
        "WMaxTime": "2001-07-29 23:14:00",
        "WSGust": "16.0",
        "WDGust": "60.0",
        "WGustTime": "2001-07-29 22:32:00",
        "typhoon_name": "2001TORAJI",
        "typhoon_cht_name": "桃芝"
    },
    {
        "num": "200108",
        "stno": "467571",
        "WSMax": "10.9",
        "WDMax": "30.0",
        "WMaxTime": "2001-07-30 02:49:00",
        "WSGust": "23.5",
        "WDGust": "240.0",
        "WGustTime": "2001-07-30 13:33:00",
        "typhoon_name": "2001TORAJI",
        "typhoon_cht_name": "桃芝"
    },
    {
        "num": "200108",
        "stno": "467571",
        "WSMax": "6.8",
        "WDMax": "250.0",
        "WMaxTime": "2001-07-31 12:01:00",
        "WSGust": "16.1",
        "WDGust": "300.0",
        "WGustTime": "2001-07-31 12:10:00",
        "typhoon_name": "2001TORAJI",
        "typhoon_cht_name": "桃芝"
    },
    {
        "num": "200105",
        "stno": "467571",
        "WSMax": "5.2",
        "WDMax": "20.0",
        "WMaxTime": "2001-07-11 13:06:00",
        "WSGust": "8.7",
        "WDGust": "80.0",
        "WGustTime": "2001-07-11 13:08:00",
        "typhoon_name": "2001TRAMI",
        "typhoon_cht_name": "潭美"
    },
    {
        "num": "200104",
        "stno": "467571",
        "WSMax": "11.2",
        "WDMax": "60.0",
        "WMaxTime": "2001-07-04 02:20:00",
        "WSGust": "22.3",
        "WDGust": "80.0",
        "WGustTime": "2001-07-04 13:44:00",
        "typhoon_name": "2001UTOR",
        "typhoon_cht_name": "尤特"
    },
    {
        "num": "200104",
        "stno": "467571",
        "WSMax": "8.9",
        "WDMax": "70.0",
        "WMaxTime": "2001-07-05 00:19:00",
        "WSGust": "17.9",
        "WDGust": "130.0",
        "WGustTime": "2001-07-05 04:02:00",
        "typhoon_name": "2001UTOR",
        "typhoon_cht_name": "尤特"
    },
    {
        "num": "200107",
        "stno": "467571",
        "WSMax": "6.0",
        "WDMax": "250.0",
        "WMaxTime": "2001-07-24 12:50:00",
        "WSGust": "11.3",
        "WDGust": "280.0",
        "WGustTime": "2001-07-24 12:43:00",
        "typhoon_name": "2001YUTU",
        "typhoon_cht_name": "玉兔"
    },
    {
        "num": "200208",
        "stno": "467571",
        "WSMax": "7.7",
        "WDMax": "10.0",
        "WMaxTime": "2002-07-10 07:37:00",
        "WSGust": "13.4",
        "WDGust": "30.0",
        "WGustTime": "2002-07-10 07:31:00",
        "typhoon_name": "2002NAKRI",
        "typhoon_cht_name": "娜克莉"
    },
    {
        "num": "200205",
        "stno": "467571",
        "WSMax": "8.5",
        "WDMax": "10.0",
        "WMaxTime": "2002-07-03 17:06:00",
        "WSGust": "16.7",
        "WDGust": "40.0",
        "WGustTime": "2002-07-03 20:36:00",
        "typhoon_name": "2002RAMMASUN",
        "typhoon_cht_name": "雷馬遜"
    },
    {
        "num": "200205",
        "stno": "467571",
        "WSMax": "5.8",
        "WDMax": "300.0",
        "WMaxTime": "2002-07-04 06:07:00",
        "WSGust": "17.0",
        "WDGust": "40.0",
        "WGustTime": "2002-07-04 01:43:00",
        "typhoon_name": "2002RAMMASUN",
        "typhoon_cht_name": "雷馬遜"
    },
    {
        "num": "200216",
        "stno": "467571",
        "WSMax": "7.1",
        "WDMax": "10.0",
        "WMaxTime": "2002-09-05 13:17:00",
        "WSGust": "13.2",
        "WDGust": "30.0",
        "WGustTime": "2002-09-05 13:23:00",
        "typhoon_name": "2002SINLAKU",
        "typhoon_cht_name": "辛樂克"
    },
    {
        "num": "200216",
        "stno": "467571",
        "WSMax": "7.5",
        "WDMax": "210.0",
        "WMaxTime": "2002-09-07 12:41:00",
        "WSGust": "14.5",
        "WDGust": "260.0",
        "WGustTime": "2002-09-07 13:11:00",
        "typhoon_name": "2002SINLAKU",
        "typhoon_cht_name": "辛樂克"
    },
    {
        "num": "200313",
        "stno": "467571",
        "WSMax": "11.4",
        "WDMax": "60.0",
        "WMaxTime": "2003-09-01 22:51:00",
        "WSGust": "24.6",
        "WDGust": "110.0",
        "WGustTime": "2003-09-01 22:57:00",
        "typhoon_name": "2003DUJUAN",
        "typhoon_cht_name": "杜鵑"
    },
    {
        "num": "200313",
        "stno": "467571",
        "WSMax": "11.4",
        "WDMax": "60.0",
        "WMaxTime": "2003-09-02 00:01:00",
        "WSGust": "22.5",
        "WDGust": "140.0",
        "WGustTime": "2003-09-02 07:21:00",
        "typhoon_name": "2003DUJUAN",
        "typhoon_cht_name": "杜鵑"
    },
    {
        "num": "200319",
        "stno": "467571",
        "WSMax": "9.7",
        "WDMax": "20.0",
        "WMaxTime": "2003-11-03 10:02:00",
        "WSGust": "21.2",
        "WDGust": "60.0",
        "WGustTime": "2003-11-03 13:12:00",
        "typhoon_name": "2003MELOR",
        "typhoon_cht_name": "米勒"
    },
    {
        "num": "200305",
        "stno": "467571",
        "WSMax": "6.2",
        "WDMax": "10.0",
        "WMaxTime": "2003-06-02 13:29:00",
        "WSGust": "11.5",
        "WDGust": "30.0",
        "WGustTime": "2003-06-02 14:35:00",
        "typhoon_name": "2003NANGKA",
        "typhoon_cht_name": "南卡"
    },
    {
        "num": "200305",
        "stno": "467571",
        "WSMax": "6.3",
        "WDMax": "10.0",
        "WMaxTime": "2003-06-03 13:27:00",
        "WSGust": "10.8",
        "WDGust": "40.0",
        "WGustTime": "2003-06-03 13:27:00",
        "typhoon_name": "2003NANGKA",
        "typhoon_cht_name": "南卡"
    },
    {
        "num": "200306",
        "stno": "467571",
        "WSMax": "8.2",
        "WDMax": "30.0",
        "WMaxTime": "2003-06-17 18:06:00",
        "WSGust": "16.9",
        "WDGust": "60.0",
        "WGustTime": "2003-06-17 18:24:00",
        "typhoon_name": "2003SOUDELOR",
        "typhoon_cht_name": "蘇迪勒"
    },
    {
        "num": "200306",
        "stno": "467571",
        "WSMax": "5.3",
        "WDMax": "10.0",
        "WMaxTime": "2003-06-18 02:05:00",
        "WSGust": "9.9",
        "WDGust": "50.0",
        "WGustTime": "2003-06-18 00:38:00",
        "typhoon_name": "2003SOUDELOR",
        "typhoon_cht_name": "蘇迪勒"
    },
    {
        "num": "200417",
        "stno": "467571",
        "WSMax": "11.4",
        "WDMax": "300.0",
        "WMaxTime": "2004-08-24 23:42:00",
        "WSGust": "22.5",
        "WDGust": "350.0",
        "WGustTime": "2004-08-24 23:40:00",
        "typhoon_name": "2004AERE",
        "typhoon_cht_name": "艾利"
    },
    {
        "num": "200417",
        "stno": "467571",
        "WSMax": "11.2",
        "WDMax": "300.0",
        "WMaxTime": "2004-08-25 04:16:00",
        "WSGust": "22.2",
        "WDGust": "330.0",
        "WGustTime": "2004-08-25 04:05:00",
        "typhoon_name": "2004AERE",
        "typhoon_cht_name": "艾利"
    },
    {
        "num": "200404",
        "stno": "467571",
        "WSMax": "5.8",
        "WDMax": "10.0",
        "WMaxTime": "2004-06-08 09:41:00",
        "WSGust": "11.6",
        "WDGust": "20.0",
        "WGustTime": "2004-06-08 09:53:00",
        "typhoon_name": "2004CONSON",
        "typhoon_cht_name": "康森"
    },
    {
        "num": "200404",
        "stno": "467571",
        "WSMax": "8.6",
        "WDMax": "60.0",
        "WMaxTime": "2004-06-09 14:29:00",
        "WSGust": "17.9",
        "WDGust": "110.0",
        "WGustTime": "2004-06-09 15:57:00",
        "typhoon_name": "2004CONSON",
        "typhoon_cht_name": "康森"
    },
    {
        "num": "200420",
        "stno": "467571",
        "WSMax": "6.8",
        "WDMax": "20.0",
        "WMaxTime": "2004-09-12 00:44:00",
        "WSGust": "14.3",
        "WDGust": "40.0",
        "WGustTime": "2004-09-12 00:42:00",
        "typhoon_name": "2004HAIMA",
        "typhoon_cht_name": "海馬"
    },
    {
        "num": "200407",
        "stno": "467571",
        "WSMax": "9.2",
        "WDMax": "50.0",
        "WMaxTime": "2004-06-29 14:27:00",
        "WSGust": "21.7",
        "WDGust": "90.0",
        "WGustTime": "2004-06-29 16:08:00",
        "typhoon_name": "2004MINDULLE",
        "typhoon_cht_name": "敏督利"
    },
    {
        "num": "200407",
        "stno": "467571",
        "WSMax": "9.8",
        "WDMax": "60.0",
        "WMaxTime": "2004-06-30 21:57:00",
        "WSGust": "19.4",
        "WDGust": "80.0",
        "WGustTime": "2004-06-30 14:45:00",
        "typhoon_name": "2004MINDULLE",
        "typhoon_cht_name": "敏督利"
    },
    {
        "num": "200407",
        "stno": "467571",
        "WSMax": "11.2",
        "WDMax": "60.0",
        "WMaxTime": "2004-07-01 14:28:00",
        "WSGust": "22.7",
        "WDGust": "110.0",
        "WGustTime": "2004-07-01 14:13:00",
        "typhoon_name": "2004MINDULLE",
        "typhoon_cht_name": "敏督利"
    },
    {
        "num": "200407",
        "stno": "467571",
        "WSMax": "5.7",
        "WDMax": "200.0",
        "WMaxTime": "2004-07-02 23:52:00",
        "WSGust": "15.4",
        "WDGust": "260.0",
        "WGustTime": "2004-07-02 23:50:00",
        "typhoon_name": "2004MINDULLE",
        "typhoon_cht_name": "敏督利"
    },
    {
        "num": "200407",
        "stno": "467571",
        "WSMax": "6.4",
        "WDMax": "200.0",
        "WMaxTime": "2004-07-03 17:13:00",
        "WSGust": "19.2",
        "WDGust": "300.0",
        "WGustTime": "2004-07-03 11:38:00",
        "typhoon_name": "2004MINDULLE",
        "typhoon_cht_name": "敏督利"
    },
    {
        "num": "200427",
        "stno": "467571",
        "WSMax": "6.2",
        "WDMax": "10.0",
        "WMaxTime": "2004-12-04 05:07:00",
        "WSGust": "13.4",
        "WDGust": "40.0",
        "WGustTime": "2004-12-04 05:01:00",
        "typhoon_name": "2004NANMADOL",
        "typhoon_cht_name": "南瑪都"
    },
    {
        "num": "200424",
        "stno": "467571",
        "WSMax": "9.6",
        "WDMax": "30.0",
        "WMaxTime": "2004-10-24 15:10:00",
        "WSGust": "20.8",
        "WDGust": "90.0",
        "WGustTime": "2004-10-24 14:40:00",
        "typhoon_name": "2004NOCK-TEN",
        "typhoon_cht_name": "納坦"
    },
    {
        "num": "200424",
        "stno": "467571",
        "WSMax": "10.2",
        "WDMax": "10.0",
        "WMaxTime": "2004-10-25 09:56:00",
        "WSGust": "24.6",
        "WDGust": "70.0",
        "WGustTime": "2004-10-25 08:37:00",
        "typhoon_name": "2004NOCK-TEN",
        "typhoon_cht_name": "納坦"
    },
    {
        "num": "200424",
        "stno": "467571",
        "WSMax": "6.5",
        "WDMax": "50.0",
        "WMaxTime": "2004-10-26 20:54:00",
        "WSGust": "14.1",
        "WDGust": "90.0",
        "WGustTime": "2004-10-26 13:48:00",
        "typhoon_name": "2004NOCK-TEN",
        "typhoon_cht_name": "納坦"
    },
    {
        "num": "200413",
        "stno": "467571",
        "WSMax": "5.9",
        "WDMax": "360.0",
        "WMaxTime": "2004-08-11 15:57:00",
        "WSGust": "13.1",
        "WDGust": "50.0",
        "WGustTime": "2004-08-11 13:02:00",
        "typhoon_name": "2004RANANIM",
        "typhoon_cht_name": "蘭寧"
    },
    {
        "num": "200518",
        "stno": "467571",
        "WSMax": "7.8",
        "WDMax": "60.0",
        "WMaxTime": "2005-09-22 14:30:00",
        "WSGust": "19.0",
        "WDGust": "100.0",
        "WGustTime": "2005-09-22 13:35:00",
        "typhoon_name": "2005DAMREY",
        "typhoon_cht_name": "丹瑞"
    },
    {
        "num": "200518",
        "stno": "467571",
        "WSMax": "8.2",
        "WDMax": "80.0",
        "WMaxTime": "2005-09-23 01:34:00",
        "WSGust": "18.4",
        "WDGust": "160.0",
        "WGustTime": "2005-09-23 01:28:00",
        "typhoon_name": "2005DAMREY",
        "typhoon_cht_name": "丹瑞"
    },
    {
        "num": "200505",
        "stno": "467571",
        "WSMax": "7.7",
        "WDMax": "20.0",
        "WMaxTime": "2005-07-17 23:08:00",
        "WSGust": "21.1",
        "WDGust": "100.0",
        "WGustTime": "2005-07-17 22:53:00",
        "typhoon_name": "2005HAITANG",
        "typhoon_cht_name": "海棠"
    },
    {
        "num": "200505",
        "stno": "467571",
        "WSMax": "9.9",
        "WDMax": "20.0",
        "WMaxTime": "2005-07-18 04:32:00",
        "WSGust": "25.8",
        "WDGust": "60.0",
        "WGustTime": "2005-07-18 05:49:00",
        "typhoon_name": "2005HAITANG",
        "typhoon_cht_name": "海棠"
    },
    {
        "num": "200505",
        "stno": "467571",
        "WSMax": "5.8",
        "WDMax": "180.0",
        "WMaxTime": "2005-07-19 09:09:00",
        "WSGust": "14.4",
        "WDGust": "250.0",
        "WGustTime": "2005-07-19 10:43:00",
        "typhoon_name": "2005HAITANG",
        "typhoon_cht_name": "海棠"
    },
    {
        "num": "200519",
        "stno": "467571",
        "WSMax": "11.4",
        "WDMax": "70.0",
        "WMaxTime": "2005-10-02 07:55:00",
        "WSGust": "22.8",
        "WDGust": "130.0",
        "WGustTime": "2005-10-02 07:41:00",
        "typhoon_name": "2005LONGWANG",
        "typhoon_cht_name": "龍王"
    },
    {
        "num": "200509",
        "stno": "467571",
        "WSMax": "5.6",
        "WDMax": "360.0",
        "WMaxTime": "2005-08-04 14:30:00",
        "WSGust": "13.8",
        "WDGust": "40.0",
        "WGustTime": "2005-08-04 11:27:00",
        "typhoon_name": "2005MATSA",
        "typhoon_cht_name": "馬莎"
    },
    {
        "num": "200509",
        "stno": "467571",
        "WSMax": "7.6",
        "WDMax": "300.0",
        "WMaxTime": "2005-08-05 05:31:00",
        "WSGust": "18.4",
        "WDGust": "20.0",
        "WGustTime": "2005-08-05 02:09:00",
        "typhoon_name": "2005MATSA",
        "typhoon_cht_name": "馬莎"
    },
    {
        "num": "200510",
        "stno": "467571",
        "WSMax": "10.0",
        "WDMax": "60.0",
        "WMaxTime": "2005-08-12 07:28:00",
        "WSGust": "21.5",
        "WDGust": "130.0",
        "WGustTime": "2005-08-12 07:57:00",
        "typhoon_name": "2005SANVU",
        "typhoon_cht_name": "珊瑚"
    },
    {
        "num": "200513",
        "stno": "467571",
        "WSMax": "14.4",
        "WDMax": "10.0",
        "WMaxTime": "2005-08-31 23:07:00",
        "WSGust": "29.9",
        "WDGust": "90.0",
        "WGustTime": "2005-08-31 23:07:00",
        "typhoon_name": "2005TALIM",
        "typhoon_cht_name": "泰利"
    },
    {
        "num": "200513",
        "stno": "467571",
        "WSMax": "12.1",
        "WDMax": "20.0",
        "WMaxTime": "2005-09-01 00:32:00",
        "WSGust": "24.6",
        "WDGust": "50.0",
        "WGustTime": "2005-09-01 00:13:00",
        "typhoon_name": "2005TALIM",
        "typhoon_cht_name": "泰利"
    },
    {
        "num": "200604",
        "stno": "467571",
        "WSMax": "8.5",
        "WDMax": "20.0",
        "WMaxTime": "2006-07-13 15:42:00",
        "WSGust": "19.1",
        "WDGust": "80.0",
        "WGustTime": "2006-07-13 15:27:00",
        "typhoon_name": "2006BILIS",
        "typhoon_cht_name": "碧利斯"
    },
    {
        "num": "200604",
        "stno": "467571",
        "WSMax": "6.8",
        "WDMax": "190.0",
        "WMaxTime": "2006-07-14 06:01:00",
        "WSGust": "14.2",
        "WDGust": "270.0",
        "WGustTime": "2006-07-14 06:29:00",
        "typhoon_name": "2006BILIS",
        "typhoon_cht_name": "碧利斯"
    },
    {
        "num": "200609",
        "stno": "467571",
        "WSMax": "5.4",
        "WDMax": "70.0",
        "WMaxTime": "2006-08-08 15:26:00",
        "WSGust": "13.7",
        "WDGust": "70.0",
        "WGustTime": "2006-08-08 23:28:00",
        "typhoon_name": "2006BOPHA",
        "typhoon_cht_name": "寶發"
    },
    {
        "num": "200609",
        "stno": "467571",
        "WSMax": "8.5",
        "WDMax": "70.0",
        "WMaxTime": "2006-08-09 10:23:00",
        "WSGust": "23.6",
        "WDGust": "120.0",
        "WGustTime": "2006-08-09 09:13:00",
        "typhoon_name": "2006BOPHA",
        "typhoon_cht_name": "寶發"
    },
    {
        "num": "200601",
        "stno": "467571",
        "WSMax": "5.5",
        "WDMax": "290.0",
        "WMaxTime": "2006-05-18 22:29:00",
        "WSGust": "14.5",
        "WDGust": "330.0",
        "WGustTime": "2006-05-18 22:07:00",
        "typhoon_name": "2006CHANCHU",
        "typhoon_cht_name": "珍珠"
    },
    {
        "num": "200605",
        "stno": "467571",
        "WSMax": "6.8",
        "WDMax": "40.0",
        "WMaxTime": "2006-07-24 13:32:00",
        "WSGust": "20.0",
        "WDGust": "100.0",
        "WGustTime": "2006-07-24 23:00:00",
        "typhoon_name": "2006KAEMI",
        "typhoon_cht_name": "凱米"
    },
    {
        "num": "200605",
        "stno": "467571",
        "WSMax": "8.4",
        "WDMax": "80.0",
        "WMaxTime": "2006-07-25 05:15:00",
        "WSGust": "20.5",
        "WDGust": "140.0",
        "WGustTime": "2006-07-25 05:06:00",
        "typhoon_name": "2006KAEMI",
        "typhoon_cht_name": "凱米"
    },
    {
        "num": "200613",
        "stno": "467571",
        "WSMax": "7.7",
        "WDMax": "30.0",
        "WMaxTime": "2006-09-15 14:43:00",
        "WSGust": "17.0",
        "WDGust": "70.0",
        "WGustTime": "2006-09-15 14:42:00",
        "typhoon_name": "2006SHANSHAN",
        "typhoon_cht_name": "珊珊"
    },
    {
        "num": "200613",
        "stno": "467571",
        "WSMax": "5.0",
        "WDMax": "10.0",
        "WMaxTime": "2006-09-16 03:45:00",
        "WSGust": "13.8",
        "WDGust": "50.0",
        "WGustTime": "2006-09-16 05:17:00",
        "typhoon_name": "2006SHANSHAN",
        "typhoon_cht_name": "珊珊"
    },
    {
        "num": "200715",
        "stno": "467571",
        "WSMax": "8.0",
        "WDMax": "20.0",
        "WMaxTime": "2007-10-05 23:26:00",
        "WSGust": "19.5",
        "WDGust": "130.0",
        "WGustTime": "2007-10-05 23:20:00",
        "typhoon_name": "2007KROSA",
        "typhoon_cht_name": "柯羅莎"
    },
    {
        "num": "200715",
        "stno": "467571",
        "WSMax": "13.2",
        "WDMax": "360.0",
        "WMaxTime": "2007-10-06 14:50:00",
        "WSGust": "32.2",
        "WDGust": "70.0",
        "WGustTime": "2007-10-06 14:26:00",
        "typhoon_name": "2007KROSA",
        "typhoon_cht_name": "柯羅莎"
    },
    {
        "num": "200723",
        "stno": "467571",
        "WSMax": "7.4",
        "WDMax": "20.0",
        "WMaxTime": "2007-11-27 00:09:00",
        "WSGust": "17.6",
        "WDGust": "100.0",
        "WGustTime": "2007-11-27 00:35:00",
        "typhoon_name": "2007MITAG",
        "typhoon_cht_name": "米塔"
    },
    {
        "num": "200706",
        "stno": "467571",
        "WSMax": "7.0",
        "WDMax": "70.0",
        "WMaxTime": "2007-08-08 05:58:00",
        "WSGust": "15.0",
        "WDGust": "130.0",
        "WGustTime": "2007-08-08 06:48:00",
        "typhoon_name": "2007PABUK",
        "typhoon_cht_name": "帕布"
    },
    {
        "num": "200708",
        "stno": "467571",
        "WSMax": "6.8",
        "WDMax": "20.0",
        "WMaxTime": "2007-08-17 19:56:00",
        "WSGust": "16.1",
        "WDGust": "110.0",
        "WGustTime": "2007-08-17 12:19:00",
        "typhoon_name": "2007SEPAT",
        "typhoon_cht_name": "聖帕"
    },
    {
        "num": "200708",
        "stno": "467571",
        "WSMax": "10.3",
        "WDMax": "20.0",
        "WMaxTime": "2007-08-18 05:54:00",
        "WSGust": "23.8",
        "WDGust": "120.0",
        "WGustTime": "2007-08-18 07:49:00",
        "typhoon_name": "2007SEPAT",
        "typhoon_cht_name": "聖帕"
    },
    {
        "num": "200712",
        "stno": "467571",
        "WSMax": "7.3",
        "WDMax": "300.0",
        "WMaxTime": "2007-09-18 16:17:00",
        "WSGust": "18.0",
        "WDGust": "360.0",
        "WGustTime": "2007-09-18 14:55:00",
        "typhoon_name": "2007WIPHA",
        "typhoon_cht_name": "韋帕"
    },
    {
        "num": "200808",
        "stno": "467571",
        "WSMax": "7.1",
        "WDMax": "20.0",
        "WMaxTime": "2008-07-27 23:06:00",
        "WSGust": "18.8",
        "WDGust": "100.0",
        "WGustTime": "2008-07-27 14:36:00",
        "typhoon_name": "2008FUNG-WONG",
        "typhoon_cht_name": "鳳凰"
    },
    {
        "num": "200808",
        "stno": "467571",
        "WSMax": "9.5",
        "WDMax": "20.0",
        "WMaxTime": "2008-07-28 06:11:00",
        "WSGust": "21.6",
        "WDGust": "90.0",
        "WGustTime": "2008-07-28 06:22:00",
        "typhoon_name": "2008FUNG-WONG",
        "typhoon_cht_name": "鳳凰"
    },
    {
        "num": "200814",
        "stno": "467571",
        "WSMax": "8.4",
        "WDMax": "70.0",
        "WMaxTime": "2008-09-22 15:07:00",
        "WSGust": "19.6",
        "WDGust": "110.0",
        "WGustTime": "2008-09-22 14:04:00",
        "typhoon_name": "2008HAGUPIT",
        "typhoon_cht_name": "哈格比"
    },
    {
        "num": "200814",
        "stno": "467571",
        "WSMax": "6.8",
        "WDMax": "70.0",
        "WMaxTime": "2008-09-23 00:21:00",
        "WSGust": "18.3",
        "WDGust": "140.0",
        "WGustTime": "2008-09-23 00:19:00",
        "typhoon_name": "2008HAGUPIT",
        "typhoon_cht_name": "哈格比"
    },
    {
        "num": "200815",
        "stno": "467571",
        "WSMax": "5.9",
        "WDMax": "30.0",
        "WMaxTime": "2008-09-27 02:34:00",
        "WSGust": "13.8",
        "WDGust": "100.0",
        "WGustTime": "2008-09-27 23:30:00",
        "typhoon_name": "2008JANGMI",
        "typhoon_cht_name": "薔密"
    },
    {
        "num": "200815",
        "stno": "467571",
        "WSMax": "13.8",
        "WDMax": "10.0",
        "WMaxTime": "2008-09-28 16:35:00",
        "WSGust": "33.9",
        "WDGust": "110.0",
        "WGustTime": "2008-09-28 16:51:00",
        "typhoon_name": "2008JANGMI",
        "typhoon_cht_name": "薔密"
    },
    {
        "num": "200807",
        "stno": "467571",
        "WSMax": "5.9",
        "WDMax": "360.0",
        "WMaxTime": "2008-07-17 23:51:00",
        "WSGust": "11.7",
        "WDGust": "80.0",
        "WGustTime": "2008-07-17 09:04:00",
        "typhoon_name": "2008KALMAEGI",
        "typhoon_cht_name": "卡玫基"
    },
    {
        "num": "200807",
        "stno": "467571",
        "WSMax": "8.5",
        "WDMax": "180.0",
        "WMaxTime": "2008-07-18 09:53:00",
        "WSGust": "18.7",
        "WDGust": "220.0",
        "WGustTime": "2008-07-18 09:15:00",
        "typhoon_name": "2008KALMAEGI",
        "typhoon_cht_name": "卡玫基"
    },
    {
        "num": "200813",
        "stno": "467571",
        "WSMax": "7.5",
        "WDMax": "10.0",
        "WMaxTime": "2008-09-12 20:01:00",
        "WSGust": "17.6",
        "WDGust": "50.0",
        "WGustTime": "2008-09-12 20:01:00",
        "typhoon_name": "2008SINLAKU",
        "typhoon_cht_name": "辛樂克"
    },
    {
        "num": "200813",
        "stno": "467571",
        "WSMax": "8.7",
        "WDMax": "10.0",
        "WMaxTime": "2008-09-13 10:13:00",
        "WSGust": "23.6",
        "WDGust": "40.0",
        "WGustTime": "2008-09-13 21:37:00",
        "typhoon_name": "2008SINLAKU",
        "typhoon_cht_name": "辛樂克"
    },
    {
        "num": "200813",
        "stno": "467571",
        "WSMax": "6.5",
        "WDMax": "280.0",
        "WMaxTime": "2008-09-14 17:15:00",
        "WSGust": "18.0",
        "WDGust": "320.0",
        "WGustTime": "2008-09-14 17:07:00",
        "typhoon_name": "2008SINLAKU",
        "typhoon_cht_name": "辛樂克"
    },
    {
        "num": "200903",
        "stno": "467571",
        "WSMax": "5.1",
        "WDMax": "190.0",
        "WMaxTime": "2009-06-22 09:56:00",
        "WSGust": "15.0",
        "WDGust": "320.0",
        "WGustTime": "2009-06-22 20:29:00",
        "typhoon_name": "2009LINFA",
        "typhoon_cht_name": "蓮花"
    },
    {
        "num": "200908",
        "stno": "467571",
        "WSMax": "6.0",
        "WDMax": "360.0",
        "WMaxTime": "2009-08-06 22:01:00",
        "WSGust": "15.4",
        "WDGust": "90.0",
        "WGustTime": "2009-08-06 23:56:00",
        "typhoon_name": "2009MORAKOT",
        "typhoon_cht_name": "莫拉克"
    },
    {
        "num": "200908",
        "stno": "467571",
        "WSMax": "9.3",
        "WDMax": "20.0",
        "WMaxTime": "2009-08-07 12:43:00",
        "WSGust": "24.4",
        "WDGust": "40.0",
        "WGustTime": "2009-08-07 21:49:00",
        "typhoon_name": "2009MORAKOT",
        "typhoon_cht_name": "莫拉克"
    },
    {
        "num": "200908",
        "stno": "467571",
        "WSMax": "9.5",
        "WDMax": "20.0",
        "WMaxTime": "2009-08-08 00:27:00",
        "WSGust": "21.5",
        "WDGust": "70.0",
        "WGustTime": "2009-08-08 00:24:00",
        "typhoon_name": "2009MORAKOT",
        "typhoon_cht_name": "莫拉克"
    },
    {
        "num": "200908",
        "stno": "467571",
        "WSMax": "5.7",
        "WDMax": "190.0",
        "WMaxTime": "2009-08-09 05:03:00",
        "WSGust": "15.3",
        "WDGust": "290.0",
        "WGustTime": "2009-08-09 05:19:00",
        "typhoon_name": "2009MORAKOT",
        "typhoon_cht_name": "莫拉克"
    },
    {
        "num": "200917",
        "stno": "467571",
        "WSMax": "9.1",
        "WDMax": "20.0",
        "WMaxTime": "2009-10-04 18:17:00",
        "WSGust": "22.7",
        "WDGust": "70.0",
        "WGustTime": "2009-10-04 12:21:00",
        "typhoon_name": "2009PARMA",
        "typhoon_cht_name": "芭瑪"
    },
    {
        "num": "200917",
        "stno": "467571",
        "WSMax": "7.8",
        "WDMax": "30.0",
        "WMaxTime": "2009-10-05 01:24:00",
        "WSGust": "21.0",
        "WDGust": "90.0",
        "WGustTime": "2009-10-05 01:24:00",
        "typhoon_name": "2009PARMA",
        "typhoon_cht_name": "芭瑪"
    },
    {
        "num": "200917",
        "stno": "467571",
        "WSMax": "6.8",
        "WDMax": "30.0",
        "WMaxTime": "2009-10-06 12:29:00",
        "WSGust": "15.2",
        "WDGust": "100.0",
        "WGustTime": "2009-10-06 10:56:00",
        "typhoon_name": "2009PARMA",
        "typhoon_cht_name": "芭瑪"
    },
    {
        "num": "201011",
        "stno": "467571",
        "WSMax": "5.5",
        "WDMax": "10.0",
        "WMaxTime": "2010-09-18 22:51:00",
        "WSGust": "12.2",
        "WDGust": "80.0",
        "WGustTime": "2010-09-18 22:44:00",
        "typhoon_name": "2010FANAPI",
        "typhoon_cht_name": "凡那比"
    },
    {
        "num": "201011",
        "stno": "467571",
        "WSMax": "8.0",
        "WDMax": "20.0",
        "WMaxTime": "2010-09-19 15:32:00",
        "WSGust": "20.4",
        "WDGust": "160.0",
        "WGustTime": "2010-09-19 19:14:00",
        "typhoon_name": "2010FANAPI",
        "typhoon_cht_name": "凡那比"
    },
    {
        "num": "201013",
        "stno": "467571",
        "WSMax": "5.9",
        "WDMax": "70.0",
        "WMaxTime": "2010-10-22 04:03:00",
        "WSGust": "16.2",
        "WDGust": "100.0",
        "WGustTime": "2010-10-22 11:06:00",
        "typhoon_name": "2010MEGI",
        "typhoon_cht_name": "梅姬"
    },
    {
        "num": "201105",
        "stno": "467571",
        "WSMax": "6.0",
        "WDMax": "20.0",
        "WMaxTime": "2011-06-24 15:13:00",
        "WSGust": "14.4",
        "WDGust": "10.0",
        "WGustTime": "2011-06-24 11:06:00",
        "typhoon_name": "2011MEARI",
        "typhoon_cht_name": "米雷"
    },
    {
        "num": "201111",
        "stno": "467571",
        "WSMax": "6.8",
        "WDMax": "60.0",
        "WMaxTime": "2011-08-28 18:55:00",
        "WSGust": "17.2",
        "WDGust": "50.0",
        "WGustTime": "2011-08-28 18:53:00",
        "typhoon_name": "2011NANMADOL",
        "typhoon_cht_name": "南瑪都"
    },
    {
        "num": "201111",
        "stno": "467571",
        "WSMax": "7.0",
        "WDMax": "60.0",
        "WMaxTime": "2011-08-29 10:35:00",
        "WSGust": "16.7",
        "WDGust": "70.0",
        "WGustTime": "2011-08-29 07:49:00",
        "typhoon_name": "2011NANMADOL",
        "typhoon_cht_name": "南瑪都"
    },
    {
        "num": "201102",
        "stno": "467571",
        "WSMax": "6.0",
        "WDMax": "20.0",
        "WMaxTime": "2011-05-28 06:13:00",
        "WSGust": "15.4",
        "WDGust": "20.0",
        "WGustTime": "2011-05-28 05:54:00",
        "typhoon_name": "2011SONGDA",
        "typhoon_cht_name": "桑達"
    },
    {
        "num": "201217",
        "stno": "467571",
        "WSMax": "6.7",
        "WDMax": "30.0",
        "WMaxTime": "2012-09-28 12:43:00",
        "WSGust": "16.8",
        "WDGust": "20.0",
        "WGustTime": "2012-09-28 16:38:00",
        "typhoon_name": "2012JELAWAT",
        "typhoon_cht_name": "杰拉華"
    },
    {
        "num": "201209",
        "stno": "467571",
        "WSMax": "5.8",
        "WDMax": "20.0",
        "WMaxTime": "2012-07-31 16:58:00",
        "WSGust": "13.7",
        "WDGust": "30.0",
        "WGustTime": "2012-07-31 21:19:00",
        "typhoon_name": "2012SAOLA",
        "typhoon_cht_name": "蘇拉"
    },
    {
        "num": "201209",
        "stno": "467571",
        "WSMax": "9.9",
        "WDMax": "10.0",
        "WMaxTime": "2012-08-01 22:59:00",
        "WSGust": "25.5",
        "WDGust": "30.0",
        "WGustTime": "2012-08-01 22:08:00",
        "typhoon_name": "2012SAOLA",
        "typhoon_cht_name": "蘇拉"
    },
    {
        "num": "201209",
        "stno": "467571",
        "WSMax": "9.1",
        "WDMax": "360.0",
        "WMaxTime": "2012-08-02 07:53:00",
        "WSGust": "22.4",
        "WDGust": "360.0",
        "WGustTime": "2012-08-02 03:11:00",
        "typhoon_name": "2012SAOLA",
        "typhoon_cht_name": "蘇拉"
    },
    {
        "num": "201205",
        "stno": "467571",
        "WSMax": "5.3",
        "WDMax": "20.0",
        "WMaxTime": "2012-06-20 20:42:00",
        "WSGust": "12.3",
        "WDGust": "360.0",
        "WGustTime": "2012-06-20 20:15:00",
        "typhoon_name": "2012TALIM",
        "typhoon_cht_name": "泰利"
    },
    {
        "num": "201214",
        "stno": "467571",
        "WSMax": "6.1",
        "WDMax": "20.0",
        "WMaxTime": "2012-08-22 15:39:00",
        "WSGust": "14.0",
        "WDGust": "10.0",
        "WGustTime": "2012-08-22 16:47:00",
        "typhoon_name": "2012TEMBIN",
        "typhoon_cht_name": "天秤"
    },
    {
        "num": "201214",
        "stno": "467571",
        "WSMax": "6.1",
        "WDMax": "20.0",
        "WMaxTime": "2012-08-23 14:49:00",
        "WSGust": "13.1",
        "WDGust": "10.0",
        "WGustTime": "2012-08-23 22:39:00",
        "typhoon_name": "2012TEMBIN",
        "typhoon_cht_name": "天秤"
    },
    {
        "num": "201214",
        "stno": "467571",
        "WSMax": "7.8",
        "WDMax": "80.0",
        "WMaxTime": "2012-08-24 10:58:00",
        "WSGust": "21.7",
        "WDGust": "90.0",
        "WGustTime": "2012-08-24 07:32:00",
        "typhoon_name": "2012TEMBIN",
        "typhoon_cht_name": "天秤"
    },
    {
        "num": "201214",
        "stno": "467571",
        "WSMax": "5.0",
        "WDMax": "110.0",
        "WMaxTime": "2012-08-25 00:14:00",
        "WSGust": "11.6",
        "WDGust": "130.0",
        "WGustTime": "2012-08-25 00:09:00",
        "typhoon_name": "2012TEMBIN",
        "typhoon_cht_name": "天秤"
    },
    {
        "num": "201323",
        "stno": "467571",
        "WSMax": "5.4",
        "WDMax": "360.0",
        "WMaxTime": "2013-10-05 22:15:00",
        "WSGust": "13.2",
        "WDGust": "40.0",
        "WGustTime": "2013-10-05 09:56:00",
        "typhoon_name": "2013FITOW",
        "typhoon_cht_name": "菲特"
    },
    {
        "num": "201323",
        "stno": "467571",
        "WSMax": "5.7",
        "WDMax": "360.0",
        "WMaxTime": "2013-10-06 03:33:00",
        "WSGust": "14.6",
        "WDGust": "360.0",
        "WGustTime": "2013-10-06 06:05:00",
        "typhoon_name": "2013FITOW",
        "typhoon_cht_name": "菲特"
    },
    {
        "num": "201307",
        "stno": "467571",
        "WSMax": "7.9",
        "WDMax": "360.0",
        "WMaxTime": "2013-07-12 20:23:00",
        "WSGust": "21.0",
        "WDGust": "360.0",
        "WGustTime": "2013-07-12 23:54:00",
        "typhoon_name": "2013SOULIK",
        "typhoon_cht_name": "蘇力"
    },
    {
        "num": "201307",
        "stno": "467571",
        "WSMax": "10.8",
        "WDMax": "360.0",
        "WMaxTime": "2013-07-13 05:41:00",
        "WSGust": "29.7",
        "WDGust": "340.0",
        "WGustTime": "2013-07-13 04:28:00",
        "typhoon_name": "2013SOULIK",
        "typhoon_cht_name": "蘇力"
    },
    {
        "num": "201312",
        "stno": "467571",
        "WSMax": "5.7",
        "WDMax": "270.0",
        "WMaxTime": "2013-08-21 20:26:00",
        "WSGust": "14.8",
        "WDGust": "270.0",
        "WGustTime": "2013-08-21 20:24:00",
        "typhoon_name": "2013TRAMI",
        "typhoon_cht_name": "潭美"
    },
    {
        "num": "201319",
        "stno": "467571",
        "WSMax": "5.8",
        "WDMax": "10.0",
        "WMaxTime": "2013-09-20 13:18:00",
        "WSGust": "13.9",
        "WDGust": "30.0",
        "WGustTime": "2013-09-20 23:57:00",
        "typhoon_name": "2013USAGI",
        "typhoon_cht_name": "天兔"
    },
    {
        "num": "201319",
        "stno": "467571",
        "WSMax": "8.2",
        "WDMax": "60.0",
        "WMaxTime": "2013-09-21 18:22:00",
        "WSGust": "22.8",
        "WDGust": "60.0",
        "WGustTime": "2013-09-21 18:06:00",
        "typhoon_name": "2013USAGI",
        "typhoon_cht_name": "天兔"
    },
    {
        "num": "201319",
        "stno": "467571",
        "WSMax": "7.8",
        "WDMax": "70.0",
        "WMaxTime": "2013-09-22 00:01:00",
        "WSGust": "17.5",
        "WDGust": "90.0",
        "WGustTime": "2013-09-22 00:16:00",
        "typhoon_name": "2013USAGI",
        "typhoon_cht_name": "天兔"
    },
    {
        "num": "201416",
        "stno": "467571",
        "WSMax": "5.3",
        "WDMax": "10.0",
        "WMaxTime": "2014-09-20 15:21:00",
        "WSGust": "12.2",
        "WDGust": "10.0",
        "WGustTime": "2014-09-20 15:25:00",
        "typhoon_name": "2014FUNG-WONG",
        "typhoon_cht_name": "鳳凰"
    },
    {
        "num": "201410",
        "stno": "467571",
        "WSMax": "7.5",
        "WDMax": "30.0",
        "WMaxTime": "2014-07-22 23:11:00",
        "WSGust": "19.9",
        "WDGust": "60.0",
        "WGustTime": "2014-07-22 23:09:00",
        "typhoon_name": "2014MATMO",
        "typhoon_cht_name": "麥德姆"
    },
    {
        "num": "201410",
        "stno": "467571",
        "WSMax": "8.0",
        "WDMax": "60.0",
        "WMaxTime": "2014-07-23 02:53:00",
        "WSGust": "18.5",
        "WDGust": "40.0",
        "WGustTime": "2014-07-23 00:29:00",
        "typhoon_name": "2014MATMO",
        "typhoon_cht_name": "麥德姆"
    },
    {
        "num": "201509",
        "stno": "467571",
        "WSMax": "5.7",
        "WDMax": "360.0",
        "WMaxTime": "2015-07-10 06:17:00",
        "WSGust": "13.9",
        "WDGust": "360.0",
        "WGustTime": "2015-07-10 08:28:00",
        "typhoon_name": "2015CHAN-HOM",
        "typhoon_cht_name": "昌鴻"
    },
    {
        "num": "201521",
        "stno": "467571",
        "WSMax": "12.6",
        "WDMax": "10.0",
        "WMaxTime": "2015-09-28 18:19:00",
        "WSGust": "30.6",
        "WDGust": "30.0",
        "WGustTime": "2015-09-28 18:17:00",
        "typhoon_name": "2015DUJUAN",
        "typhoon_cht_name": "杜鵑"
    },
    {
        "num": "201515",
        "stno": "467571",
        "WSMax": "6.2",
        "WDMax": "80.0",
        "WMaxTime": "2015-08-21 15:04:00",
        "WSGust": "14.9",
        "WDGust": "80.0",
        "WGustTime": "2015-08-21 15:04:00",
        "typhoon_name": "2015GONI",
        "typhoon_cht_name": "天鵝"
    },
    {
        "num": "201515",
        "stno": "467571",
        "WSMax": "7.3",
        "WDMax": "60.0",
        "WMaxTime": "2015-08-22 16:34:00",
        "WSGust": "17.4",
        "WDGust": "30.0",
        "WGustTime": "2015-08-22 09:46:00",
        "typhoon_name": "2015GONI",
        "typhoon_cht_name": "天鵝"
    },
    {
        "num": "201515",
        "stno": "467571",
        "WSMax": "5.6",
        "WDMax": "20.0",
        "WMaxTime": "2015-08-23 17:03:00",
        "WSGust": "12.4",
        "WDGust": "20.0",
        "WGustTime": "2015-08-23 16:54:00",
        "typhoon_name": "2015GONI",
        "typhoon_cht_name": "天鵝"
    },
    {
        "num": "201510",
        "stno": "467571",
        "WSMax": "5.2",
        "WDMax": "20.0",
        "WMaxTime": "2015-07-09 14:17:00",
        "WSGust": "12.2",
        "WDGust": "10.0",
        "WGustTime": "2015-07-09 17:06:00",
        "typhoon_name": "2015LINFA",
        "typhoon_cht_name": "蓮花"
    },
    {
        "num": "201513",
        "stno": "467571",
        "WSMax": "8.2",
        "WDMax": "20.0",
        "WMaxTime": "2015-08-07 23:49:00",
        "WSGust": "20.1",
        "WDGust": "10.0",
        "WGustTime": "2015-08-07 20:39:00",
        "typhoon_name": "2015SOUDELOR",
        "typhoon_cht_name": "蘇迪勒"
    },
    {
        "num": "201513",
        "stno": "467571",
        "WSMax": "12.6",
        "WDMax": "20.0",
        "WMaxTime": "2015-08-08 03:20:00",
        "WSGust": "30.4",
        "WDGust": "40.0",
        "WGustTime": "2015-08-08 05:06:00",
        "typhoon_name": "2015SOUDELOR",
        "typhoon_cht_name": "蘇迪勒"
    },
    {
        "num": "201619",
        "stno": "467571",
        "WSMax": "5.2",
        "WDMax": "60.0",
        "WMaxTime": "2016-10-06 04:50:00",
        "WSGust": "12.4",
        "WDGust": "80.0",
        "WGustTime": "2016-10-06 00:42:00",
        "typhoon_name": "2016AERE",
        "typhoon_cht_name": "艾利"
    },
    {
        "num": "201617",
        "stno": "467571",
        "WSMax": "5.3",
        "WDMax": "30.0",
        "WMaxTime": "2016-09-26 10:11:00",
        "WSGust": "12.9",
        "WDGust": "20.0",
        "WGustTime": "2016-09-26 16:45:00",
        "typhoon_name": "2016MEGI",
        "typhoon_cht_name": "梅姬"
    },
    {
        "num": "201617",
        "stno": "467571",
        "WSMax": "15.1",
        "WDMax": "10.0",
        "WMaxTime": "2016-09-27 14:13:00",
        "WSGust": "36.7",
        "WDGust": "50.0",
        "WGustTime": "2016-09-27 14:24:00",
        "typhoon_name": "2016MEGI",
        "typhoon_cht_name": "梅姬"
    },
    {
        "num": "201614",
        "stno": "467571",
        "WSMax": "7.4",
        "WDMax": "60.0",
        "WMaxTime": "2016-09-13 21:29:00",
        "WSGust": "18.1",
        "WDGust": "90.0",
        "WGustTime": "2016-09-13 21:17:00",
        "typhoon_name": "2016MERANTI",
        "typhoon_cht_name": "莫蘭蒂"
    },
    {
        "num": "201614",
        "stno": "467571",
        "WSMax": "7.3",
        "WDMax": "60.0",
        "WMaxTime": "2016-09-14 11:16:00",
        "WSGust": "18.8",
        "WDGust": "80.0",
        "WGustTime": "2016-09-14 15:39:00",
        "typhoon_name": "2016MERANTI",
        "typhoon_cht_name": "莫蘭蒂"
    },
    {
        "num": "201601",
        "stno": "467571",
        "WSMax": "6.1",
        "WDMax": "80.0",
        "WMaxTime": "2016-07-07 11:14:00",
        "WSGust": "16.0",
        "WDGust": "70.0",
        "WGustTime": "2016-07-07 11:29:00",
        "typhoon_name": "2016NEPARTAK",
        "typhoon_cht_name": "尼伯特"
    },
    {
        "num": "201601",
        "stno": "467571",
        "WSMax": "8.4",
        "WDMax": "60.0",
        "WMaxTime": "2016-07-08 14:08:00",
        "WSGust": "20.6",
        "WDGust": "70.0",
        "WGustTime": "2016-07-08 13:44:00",
        "typhoon_name": "2016NEPARTAK",
        "typhoon_cht_name": "尼伯特"
    },
    {
        "num": "201713",
        "stno": "467571",
        "WSMax": "6.2",
        "WDMax": "20.0",
        "WMaxTime": "2017-08-21 11:42:00",
        "WSGust": "14.7",
        "WDGust": "20.0",
        "WGustTime": "2017-08-21 12:04:00",
        "typhoon_name": "2017HATO",
        "typhoon_cht_name": "天鴿"
    },
    {
        "num": "201713",
        "stno": "467571",
        "WSMax": "5.3",
        "WDMax": "60.0",
        "WMaxTime": "2017-08-22 02:29:00",
        "WSGust": "12.5",
        "WDGust": "60.0",
        "WGustTime": "2017-08-22 02:57:00",
        "typhoon_name": "2017HATO",
        "typhoon_cht_name": "天鴿"
    },
    {
        "num": "201709",
        "stno": "467571",
        "WSMax": "9.5",
        "WDMax": "360.0",
        "WMaxTime": "2017-07-29 20:57:00",
        "WSGust": "24.4",
        "WDGust": "350.0",
        "WGustTime": "2017-07-29 20:16:00",
        "typhoon_name": "2017NESAT",
        "typhoon_cht_name": "尼莎"
    },
    {
        "num": "201709",
        "stno": "467571",
        "WSMax": "8.9",
        "WDMax": "170.0",
        "WMaxTime": "2017-07-30 00:17:00",
        "WSGust": "18.9",
        "WDGust": "190.0",
        "WGustTime": "2017-07-30 00:46:00",
        "typhoon_name": "2017NESAT",
        "typhoon_cht_name": "尼莎"
    },
    {
        "num": "201822",
        "stno": "467571",
        "WSMax": "7.5",
        "WDMax": "60.0",
        "WMaxTime": "2018-09-15 14:48:00",
        "WSGust": "17.9",
        "WDGust": "70.0",
        "WGustTime": "2018-09-15 21:50:00",
        "typhoon_name": "2018MANGKHUT",
        "typhoon_cht_name": "山竹"
    },
    {
        "num": "201808",
        "stno": "467571",
        "WSMax": "5.3",
        "WDMax": "360.0",
        "WMaxTime": "2018-07-10 21:12:00",
        "WSGust": "12.4",
        "WDGust": "360.0",
        "WGustTime": "2018-07-10 21:12:00",
        "typhoon_name": "2018MARIA",
        "typhoon_cht_name": "瑪莉亞"
    },
    {
        "num": "201808",
        "stno": "467571",
        "WSMax": "5.2",
        "WDMax": "290.0",
        "WMaxTime": "2018-07-11 02:46:00",
        "WSGust": "13.3",
        "WDGust": "290.0",
        "WGustTime": "2018-07-11 02:45:00",
        "typhoon_name": "2018MARIA",
        "typhoon_cht_name": "瑪莉亞"
    },
    {
        "num": "201911",
        "stno": "467571",
        "WSMax": "9.0",
        "WDMax": "60.0",
        "WMaxTime": "2019-08-24 17:30:00",
        "WSGust": "21.8",
        "WDGust": "60.0",
        "WGustTime": "2019-08-24 17:14:00",
        "typhoon_name": "2019BAILU",
        "typhoon_cht_name": "白鹿"
    },
    {
        "num": "201905",
        "stno": "467571",
        "WSMax": "6.3",
        "WDMax": "40.0",
        "WMaxTime": "2019-07-17 13:06:00",
        "WSGust": "21.4",
        "WDGust": "70.0",
        "WGustTime": "2019-07-17 15:54:00",
        "typhoon_name": "2019DANAS",
        "typhoon_cht_name": "丹娜絲"
    },
    {
        "num": "201905",
        "stno": "467571",
        "WSMax": "5.0",
        "WDMax": "20.0",
        "WMaxTime": "2019-07-18 01:17:00",
        "WSGust": "10.1",
        "WDGust": "20.0",
        "WGustTime": "2019-07-18 01:16:00",
        "typhoon_name": "2019DANAS",
        "typhoon_cht_name": "丹娜絲"
    },
    {
        "num": "201909",
        "stno": "467571",
        "WSMax": "5.3",
        "WDMax": "190.0",
        "WMaxTime": "2019-08-09 23:45:00",
        "WSGust": "13.3",
        "WDGust": "170.0",
        "WGustTime": "2019-08-09 23:45:00",
        "typhoon_name": "2019LEKIMA",
        "typhoon_cht_name": "利奇馬"
    },
    {
        "num": "201918",
        "stno": "467571",
        "WSMax": "6.4",
        "WDMax": "360.0",
        "WMaxTime": "2019-09-30 20:57:00",
        "WSGust": "16.2",
        "WDGust": "60.0",
        "WGustTime": "2019-09-30 18:21:00",
        "typhoon_name": "2019MITAG",
        "typhoon_cht_name": "米塔"
    },
    {
        "num": "202114",
        "stno": "467571",
        "WSMax": "5.6",
        "WDMax": "270.0",
        "WMaxTime": "2021-09-13 13:59:00",
        "WSGust": "13.2",
        "WDGust": "280.0",
        "WGustTime": "2021-09-13 15:35:00",
        "typhoon_name": "2021CHANTHU",
        "typhoon_cht_name": "璨樹"
    },
    {
        "num": "202106",
        "stno": "467571",
        "WSMax": "5.9",
        "WDMax": "10.0",
        "WMaxTime": "2021-07-23 14:12:00",
        "WSGust": "14.5",
        "WDGust": "340.0",
        "WGustTime": "2021-07-23 13:59:00",
        "typhoon_name": "2021IN-FA",
        "typhoon_cht_name": "烟花"
    },
    {
        "num": "202118",
        "stno": "467571",
        "WSMax": "6.5",
        "WDMax": "30.0",
        "WMaxTime": "2021-10-11 23:37:00",
        "WSGust": "17.5",
        "WDGust": "50.0",
        "WGustTime": "2021-10-11 23:12:00",
        "typhoon_name": "2021KOMPASU",
        "typhoon_cht_name": "圓規"
    },
    {
        "num": "202118",
        "stno": "467571",
        "WSMax": "7.5",
        "WDMax": "60.0",
        "WMaxTime": "2021-10-12 12:25:00",
        "WSGust": "18.0",
        "WDGust": "80.0",
        "WGustTime": "2021-10-12 12:35:00",
        "typhoon_name": "2021KOMPASU",
        "typhoon_cht_name": "圓規"
    },
    {
        "num": "202211",
        "stno": "467571",
        "WSMax": "5.7",
        "WDMax": "360.0",
        "WMaxTime": "2022-09-03 13:47:00",
        "WSGust": "12.9",
        "WDGust": "10.0",
        "WGustTime": "2022-09-03 12:19:00",
        "typhoon_name": "2022HINNAMNOR",
        "typhoon_cht_name": "軒嵐諾"
    },
    {
        "num": "202212",
        "stno": "467571",
        "WSMax": "5.1",
        "WDMax": "360.0",
        "WMaxTime": "2022-09-12 13:54:00",
        "WSGust": "11.5",
        "WDGust": "20.0",
        "WGustTime": "2022-09-12 15:01:00",
        "typhoon_name": "2022MUIFA",
        "typhoon_cht_name": "梅花"
    },
    {
        "num": "202220",
        "stno": "467571",
        "WSMax": "7.4",
        "WDMax": "30.0",
        "WMaxTime": "2022-10-16 21:55:00",
        "WSGust": "16.6",
        "WDGust": "60.0",
        "WGustTime": "2022-10-16 21:07:00",
        "typhoon_name": "2022NESAT",
        "typhoon_cht_name": "尼莎"
    },
    {
        "num": "202305",
        "stno": "467571",
        "WSMax": "6.0",
        "WDMax": "60.0",
        "WMaxTime": "2023-07-25 22:21:00",
        "WSGust": "16.3",
        "WDGust": "60.0",
        "WGustTime": "2023-07-25 23:53:00",
        "typhoon_name": "2023DOKSURI",
        "typhoon_cht_name": "杜蘇芮"
    },
    {
        "num": "202305",
        "stno": "467571",
        "WSMax": "6.8",
        "WDMax": "60.0",
        "WMaxTime": "2023-07-26 11:36:00",
        "WSGust": "16.0",
        "WDGust": "60.0",
        "WGustTime": "2023-07-26 07:04:00",
        "typhoon_name": "2023DOKSURI",
        "typhoon_cht_name": "杜蘇芮"
    },
    {
        "num": "202311",
        "stno": "467571",
        "WSMax": "5.0",
        "WDMax": "50.0",
        "WMaxTime": "2023-09-02 11:55:00",
        "WSGust": "11.2",
        "WDGust": "60.0",
        "WGustTime": "2023-09-02 13:11:00",
        "typhoon_name": "2023HAIKUI",
        "typhoon_cht_name": "海葵"
    },
    {
        "num": "202311",
        "stno": "467571",
        "WSMax": "7.3",
        "WDMax": "50.0",
        "WMaxTime": "2023-09-03 20:09:00",
        "WSGust": "17.4",
        "WDGust": "60.0",
        "WGustTime": "2023-09-03 20:00:00",
        "typhoon_name": "2023HAIKUI",
        "typhoon_cht_name": "海葵"
    },
    {
        "num": "202311",
        "stno": "467571",
        "WSMax": "6.4",
        "WDMax": "70.0",
        "WMaxTime": "2023-09-04 01:15:00",
        "WSGust": "15.6",
        "WDGust": "80.0",
        "WGustTime": "2023-09-04 02:57:00",
        "typhoon_name": "2023HAIKUI",
        "typhoon_cht_name": "海葵"
    },
    {
        "num": "202314",
        "stno": "467571",
        "WSMax": "5.2",
        "WDMax": "60.0",
        "WMaxTime": "2023-10-03 12:30:00",
        "WSGust": "11.7",
        "WDGust": "350.0",
        "WGustTime": "2023-10-03 09:50:00",
        "typhoon_name": "2023KOINU",
        "typhoon_cht_name": "小犬"
    },
    {
        "num": "202314",
        "stno": "467571",
        "WSMax": "5.9",
        "WDMax": "30.0",
        "WMaxTime": "2023-10-04 18:17:00",
        "WSGust": "14.6",
        "WDGust": "30.0",
        "WGustTime": "2023-10-04 22:37:00",
        "typhoon_name": "2023KOINU",
        "typhoon_cht_name": "小犬"
    },
    {
        "num": "202314",
        "stno": "467571",
        "WSMax": "7.9",
        "WDMax": "20.0",
        "WMaxTime": "2023-10-05 06:18:00",
        "WSGust": "19.7",
        "WDGust": "30.0",
        "WGustTime": "2023-10-05 08:29:00",
        "typhoon_name": "2023KOINU",
        "typhoon_cht_name": "小犬"
    },
    {
        "num": "202302",
        "stno": "467571",
        "WSMax": "6.0",
        "WDMax": "10.0",
        "WMaxTime": "2023-05-30 12:34:00",
        "WSGust": "13.6",
        "WDGust": "60.0",
        "WGustTime": "2023-05-30 09:48:00",
        "typhoon_name": "2023MAWAR",
        "typhoon_cht_name": "瑪娃"
    },
    {
        "num": "202302",
        "stno": "467571",
        "WSMax": "5.3",
        "WDMax": "30.0",
        "WMaxTime": "2023-05-31 13:38:00",
        "WSGust": "14.9",
        "WDGust": "60.0",
        "WGustTime": "2023-05-31 10:57:00",
        "typhoon_name": "2023MAWAR",
        "typhoon_cht_name": "瑪娃"
    },
    {
        "num": "202309",
        "stno": "467571",
        "WSMax": "5.4",
        "WDMax": "60.0",
        "WMaxTime": "2023-08-30 11:50:00",
        "WSGust": "12.6",
        "WDGust": "120.0",
        "WGustTime": "2023-08-30 13:33:00",
        "typhoon_name": "2023SAOLA",
        "typhoon_cht_name": "蘇拉"
    },
    {
        "num": "202309",
        "stno": "467571",
        "WSMax": "6.4",
        "WDMax": "70.0",
        "WMaxTime": "2023-08-31 13:23:00",
        "WSGust": "14.1",
        "WDGust": "90.0",
        "WGustTime": "2023-08-31 16:32:00",
        "typhoon_name": "2023SAOLA",
        "typhoon_cht_name": "蘇拉"
    },
    {
        "num": "202403",
        "stno": "467571",
        "WSMax": "6.3",
        "WDMax": "70.0",
        "WMaxTime": "2024-07-23 16:05:00",
        "WSGust": "14.3",
        "WDGust": "60.0",
        "WGustTime": "2024-07-23 14:25:00",
        "typhoon_name": "2024GAEMI",
        "typhoon_cht_name": "凱米"
    },
    {
        "num": "202403",
        "stno": "467571",
        "WSMax": "7.3",
        "WDMax": "20.0",
        "WMaxTime": "2024-07-24 18:01:00",
        "WSGust": "18.8",
        "WDGust": "360.0",
        "WGustTime": "2024-07-24 16:44:00",
        "typhoon_name": "2024GAEMI",
        "typhoon_cht_name": "凱米"
    },
    {
        "num": "202421",
        "stno": "467571",
        "WSMax": "5.8",
        "WDMax": "30.0",
        "WMaxTime": "2024-10-30 23:28:00",
        "WSGust": "16.0",
        "WDGust": "30.0",
        "WGustTime": "2024-10-30 23:45:00",
        "typhoon_name": "2024KONG-REY",
        "typhoon_cht_name": "康芮"
    },
    {
        "num": "202421",
        "stno": "467571",
        "WSMax": "10.0",
        "WDMax": "70.0",
        "WMaxTime": "2024-10-31 16:01:00",
        "WSGust": "25.2",
        "WDGust": "70.0",
        "WGustTime": "2024-10-31 15:59:00",
        "typhoon_name": "2024KONG-REY",
        "typhoon_cht_name": "康芮"
    },
    {
        "num": "202421",
        "stno": "467571",
        "WSMax": "6.8",
        "WDMax": "180.0",
        "WMaxTime": "2024-11-01 03:58:00",
        "WSGust": "16.7",
        "WDGust": "180.0",
        "WGustTime": "2024-11-01 03:50:00",
        "typhoon_name": "2024KONG-REY",
        "typhoon_cht_name": "康芮"
    },
    {
        "num": "202418",
        "stno": "467571",
        "WSMax": "7.1",
        "WDMax": "70.0",
        "WMaxTime": "2024-09-30 15:32:00",
        "WSGust": "18.9",
        "WDGust": "80.0",
        "WGustTime": "2024-09-30 15:26:00",
        "typhoon_name": "2024KRATHON",
        "typhoon_cht_name": "山陀兒"
    },
    {
        "num": "202418",
        "stno": "467571",
        "WSMax": "8.0",
        "WDMax": "40.0",
        "WMaxTime": "2024-10-02 16:43:00",
        "WSGust": "19.7",
        "WDGust": "50.0",
        "WGustTime": "2024-10-02 16:34:00",
        "typhoon_name": "2024KRATHON",
        "typhoon_cht_name": "山陀兒"
    },
    {
        "num": "202418",
        "stno": "467571",
        "WSMax": "7.4",
        "WDMax": "40.0",
        "WMaxTime": "2024-10-03 07:49:00",
        "WSGust": "17.1",
        "WDGust": "30.0",
        "WGustTime": "2024-10-03 19:01:00",
        "typhoon_name": "2024KRATHON",
        "typhoon_cht_name": "山陀兒"
    },
    {
        "num": "202418",
        "stno": "467571",
        "WSMax": "5.4",
        "WDMax": "30.0",
        "WMaxTime": "2024-10-04 14:31:00",
        "WSGust": "13.6",
        "WDGust": "50.0",
        "WGustTime": "2024-10-04 01:53:00",
        "typhoon_name": "2024KRATHON",
        "typhoon_cht_name": "山陀兒"
    }
]